appmail/__init__.py
appmail/admin.py
appmail/apps.py
appmail/forms.py
appmail/helpers.py
appmail/management/__init__.py
appmail/management/commands/__init__.py
appmail/management/commands/truncate_logged_messages.py
appmail/migrations/0001_initial.py
appmail/migrations/0002_add_template_description.py
appmail/migrations/0003_emailtemplate_test_context.py
appmail/migrations/0004_emailtemplate_is_active.py
appmail/migrations/0005_emailtemplate_from_email__reply_to.py
appmail/migrations/0006_emailtemplate_supports_attachments.py
appmail/migrations/0007_loggedemailmessage.py
appmail/migrations/0008_add_logged_message_indexes.py
appmail/migrations/0009_alter_emailtemplate_unique_together_and_more.py
appmail/migrations/__init__.py
appmail/models.py
appmail/settings.py
appmail/templates/admin/appmail/emailtemplate/change_form.html
appmail/templates/admin/appmail/loggedmessage/change_form.html
appmail/templates/admin/appmail/loggedmessage/template_name_filter.html
appmail/templates/appmail/send_test_email.html
appmail/templates/base.html
appmail/templates/base.txt
appmail/urls.py
appmail/views.py
django_appmail-8.0.dist-info/METADATA
django_appmail-8.0.dist-info/WHEEL
django_appmail-8.0.dist-info/licenses/LICENSE
django_appmail-8.0.dist-info/RECORD
